setup.py
speech2text/__init__.py
speech2text/log.py
speech2text.egg-info/PKG-INFO
speech2text.egg-info/SOURCES.txt
speech2text.egg-info/dependency_links.txt
speech2text.egg-info/entry_points.txt
speech2text.egg-info/requires.txt
speech2text.egg-info/top_level.txt
speech2text/engines/__init__.py
speech2text/engines/bing.py
speech2text/engines/ds.py
speech2text/engines/google.py
speech2text/engines/govivace.py
speech2text/engines/houndify.py
speech2text/engines/ibm.py
speech2text/engines/kaldi.py
speech2text/engines/wit.py
speech2text/engines/yandex.py