Metadata-Version: 1.0
Name: speech2text
Version: 0.2.1
Summary: Mycroft STT engine wrappers
Home-page: https://github.com/JarbasAl/speech2text
Author: jarbasAI
Author-email: jarbasai@mailfence.com
License: Apache2.0
Platform: UNKNOWN
